{
  "bg": 183, 
  "temp": "absolute", 
  "snoozeBG": 157, 
  "recieved": true, 
  "predBGs": {
    "IOB": [
      183, 
      181, 
      179, 
      177, 
      174, 
      171, 
      168, 
      165, 
      162, 
      158, 
      153, 
      149, 
      144, 
      139, 
      135, 
      130, 
      126, 
      121, 
      117, 
      113, 
      109, 
      106, 
      103, 
      100, 
      97, 
      94, 
      92, 
      90, 
      88, 
      87, 
      86, 
      85, 
      84, 
      84, 
      84, 
      83
    ]
  }, 
  "rate": 0.45, 
  "reason": "COB: 0, Dev: 0, BGI: -1.92, Target: 115; Eventual BG 97<110, bolus snooze: eventual BG range 97-157; setting current basal of 0.43 as temp", 
  "eventualBG": 97, 
  "timestamp": "2016-04-24T01:37:58.309631", 
  "duration": 30, 
  "tick": -2
}