[
  {
    "direction": "FortyFiveUp", 
    "noise": 1, 
    "sysTime": "2016-04-28T22:52:16.329-0700", 
    "xDrip_calculated_value": 164, 
    "xDrip_raw": 176, 
    "dateString": "2016-04-28T22:52:16.329-0700", 
    "sgv": 164, 
    "date": 1461909136329, 
    "xDrip_filtered": 167, 
    "xDrip_age_adjusted_raw_value": 176, 
    "unfiltered": 176000, 
    "rssi": 100, 
    "device": "xDrip-DexcomShare", 
    "filtered": 167000, 
    "xDrip_calculated_current_slope": 2.3295361893447016e-05, 
    "_id": "5722f6d765110bbfc192d956", 
    "type": "sgv"
  }, 
  {
    "direction": "Flat", 
    "noise": 1, 
    "sysTime": "2016-04-28T22:47:15.840-0700", 
    "xDrip_calculated_value": 157, 
    "xDrip_raw": 170, 
    "dateString": "2016-04-28T22:47:15.840-0700", 
    "sgv": 157, 
    "date": 1461908835840, 
    "xDrip_filtered": 163, 
    "xDrip_age_adjusted_raw_value": 170, 
    "unfiltered": 170000, 
    "rssi": 100, 
    "device": "xDrip-DexcomShare", 
    "filtered": 163000, 
    "xDrip_calculated_current_slope": 2.0021489732312683e-05, 
    "_id": "5722f58665110bbfc192d955", 
    "type": "sgv"
  }, 
  {
    "direction": "Flat", 
    "noise": 1, 
    "sysTime": "2016-04-28T22:42:16.162-0700", 
    "xDrip_calculated_value": 151, 
    "xDrip_raw": 165, 
    "dateString": "2016-04-28T22:42:16.162-0700", 
    "sgv": 151, 
    "date": 1461908536162, 
    "xDrip_filtered": 160, 
    "xDrip_age_adjusted_raw_value": 165, 
    "unfiltered": 165000, 
    "rssi": 100, 
    "device": "xDrip-DexcomShare", 
    "filtered": 160000, 
    "xDrip_calculated_current_slope": 1.3296855626065826e-05, 
    "_id": "5722f45965110bbfc192d954", 
    "type": "sgv"
  }, 
  {
    "direction": "Flat", 
    "noise": 1, 
    "sysTime": "2016-04-28T22:37:15.339-0700", 
    "xDrip_calculated_value": 147, 
    "xDrip_raw": 161, 
    "dateString": "2016-04-28T22:37:15.339-0700", 
    "sgv": 147, 
    "date": 1461908235339, 
    "xDrip_filtered": 158, 
    "xDrip_age_adjusted_raw_value": 161, 
    "unfiltered": 161000, 
    "rssi": 100, 
    "device": "xDrip-DexcomShare", 
    "filtered": 158000, 
    "xDrip_calculated_current_slope": 1.001983928177792e-05, 
    "_id": "5722f34f65110bbfc192d951", 
    "type": "sgv"
  }, 
  {
    "direction": "Flat", 
    "noise": 1, 
    "sysTime": "2016-04-28T22:32:15.933-0700", 
    "xDrip_calculated_value": 144, 
    "xDrip_raw": 159, 
    "dateString": "2016-04-28T22:32:15.933-0700", 
    "sgv": 144, 
    "date": 1461907935933, 
    "xDrip_filtered": 158, 
    "xDrip_age_adjusted_raw_value": 159, 
    "unfiltered": 159000, 
    "rssi": 100, 
    "device": "xDrip-DexcomShare", 
    "filtered": 158000, 
    "xDrip_calculated_current_slope": 3.3266799733865604e-06, 
    "_id": "5722f20065110bbfc192d94e", 
    "type": "sgv"
  }, 
  {
    "direction": "Flat", 
    "noise": 1, 
    "sysTime": "2016-04-28T22:27:15.333-0700", 
    "xDrip_calculated_value": 143, 
    "xDrip_raw": 158, 
    "dateString": "2016-04-28T22:27:15.333-0700", 
    "sgv": 143, 
    "date": 1461907635333, 
    "xDrip_filtered": 160, 
    "xDrip_age_adjusted_raw_value": 158, 
    "unfiltered": 158000, 
    "rssi": 100, 
    "device": "xDrip-DexcomShare", 
    "filtered": 160000, 
    "xDrip_calculated_current_slope": -1.0013150604460525e-05, 
    "_id": "5722f0d465110bbfc192d94c", 
    "type": "sgv"
  }, 
  {
    "direction": "Flat", 
    "noise": 1, 
    "sysTime": "2016-04-28T22:22:15.727-0700", 
    "xDrip_calculated_value": 146, 
    "xDrip_raw": 160, 
    "dateString": "2016-04-28T22:22:15.727-0700", 
    "sgv": 146, 
    "date": 1461907335727, 
    "xDrip_filtered": 165, 
    "xDrip_age_adjusted_raw_value": 160, 
    "unfiltered": 160000, 
    "rssi": 100, 
    "device": "xDrip-DexcomShare", 
    "filtered": 165000, 
    "xDrip_calculated_current_slope": -3.326336937973795e-06, 
    "_id": "5722efc965110bbfc192d94a", 
    "type": "sgv"
  }, 
  {
    "direction": "FortyFiveDown", 
    "noise": 1, 
    "sysTime": "2016-04-28T22:17:15.096-0700", 
    "xDrip_calculated_value": 147, 
    "xDrip_raw": 162, 
    "dateString": "2016-04-28T22:17:15.096-0700", 
    "sgv": 147, 
    "date": 1461907035096, 
    "xDrip_filtered": 170, 
    "xDrip_age_adjusted_raw_value": 162, 
    "unfiltered": 162000, 
    "rssi": 100, 
    "device": "xDrip-DexcomShare", 
    "filtered": 170000, 
    "xDrip_calculated_current_slope": -1.3373632546072164e-05, 
    "_id": "5722ee7b65110bbfc192d948", 
    "type": "sgv"
  }, 
  {
    "direction": "FortyFiveDown", 
    "noise": 1, 
    "sysTime": "2016-04-28T22:12:16.000-0700", 
    "xDrip_calculated_value": 151, 
    "xDrip_raw": 165, 
    "dateString": "2016-04-28T22:12:16.000-0700", 
    "sgv": 151, 
    "date": 1461906736000, 
    "xDrip_filtered": 175, 
    "xDrip_age_adjusted_raw_value": 165, 
    "unfiltered": 165000, 
    "rssi": 100, 
    "device": "xDrip-DexcomShare", 
    "filtered": 175000, 
    "xDrip_calculated_current_slope": -2.6680006670001667e-05, 
    "_id": "5722ed4f65110bbfc192d945", 
    "type": "sgv"
  }, 
  {
    "direction": "FortyFiveDown", 
    "noise": 1, 
    "sysTime": "2016-04-28T22:07:16.150-0700", 
    "xDrip_calculated_value": 159, 
    "xDrip_raw": 173, 
    "dateString": "2016-04-28T22:07:16.150-0700", 
    "sgv": 159, 
    "date": 1461906436150, 
    "xDrip_filtered": 179, 
    "xDrip_age_adjusted_raw_value": 173, 
    "unfiltered": 173000, 
    "rssi": 100, 
    "device": "xDrip-DexcomShare", 
    "filtered": 179000, 
    "xDrip_calculated_current_slope": -3.334922979953778e-05, 
    "_id": "5722ec4365110bbfc192d943", 
    "type": "sgv"
  }
]