{
  "device": "openaps://indy2", 
  "pump": {
    "battery": {
      "status": "normal", 
      "voltage": 1.37
    }, 
    "status": {
      "status": "normal", 
      "timestamp": "2016-04-21T12:51:36.000Z", 
      "bolusing": false, 
      "suspended": false
    }, 
    "reservoir": 218.225, 
    "clock": "2016-04-21T05:50:52-07:00"
  }, 
  "openaps": {
    "suggested": {
      "bg": 171, 
      "temp": "absolute", 
      "snoozeBG": 174, 
      "timestamp": "2016-04-21T12:54:31.000Z", 
      "predBGs": {
        "IOB": [
          171, 
          168, 
          164, 
          161, 
          157, 
          153, 
          149, 
          145, 
          140, 
          136, 
          131, 
          126, 
          121, 
          116, 
          111, 
          106, 
          102, 
          97, 
          93, 
          89, 
          85, 
          81, 
          78, 
          74, 
          72, 
          69, 
          67, 
          65, 
          63, 
          62, 
          60, 
          59, 
          58, 
          58, 
          57
        ]
      }, 
      "rate": 0.35, 
      "reason": "COB: 0, Dev: 28, BGI: -1.33, Target: 115; Eventual BG 110>110 but Avg. Delta -3.00 < Exp. Delta -1.1; setting current basal of 0.36 as temp", 
      "eventualBG": 110, 
      "duration": 30, 
      "tick": -3
    }, 
    "iob": [
      {
        "netbasalinsulin": 0.45, 
        "activity": 0.003, 
        "basaliob": 0.5, 
        "time": "2016-04-21T12:50:52.000Z", 
        "hightempinsulin": 0.7, 
        "bolussnooze": 0.478, 
        "iob": 0.997
      }, 
      {
        "netbasalinsulin": 0.45, 
        "activity": 0.0038, 
        "basaliob": 0.486, 
        "time": "2016-04-21T12:55:52.000Z", 
        "hightempinsulin": 0.7, 
        "bolussnooze": 0.442, 
        "iob": 0.978
      }, 
      {
        "netbasalinsulin": 0.5, 
        "activity": 0.0046, 
        "basaliob": 0.519, 
        "time": "2016-04-21T13:00:52.000Z", 
        "hightempinsulin": 0.75, 
        "bolussnooze": 0.39, 
        "iob": 1.005
      }, 
      {
        "netbasalinsulin": 0.55, 
        "activity": 0.0054, 
        "basaliob": 0.551, 
        "time": "2016-04-21T13:05:52.000Z", 
        "hightempinsulin": 0.8, 
        "bolussnooze": 0.321, 
        "iob": 1.028
      }, 
      {
        "netbasalinsulin": 0.55, 
        "activity": 0.0062, 
        "basaliob": 0.53, 
        "time": "2016-04-21T13:10:52.000Z", 
        "hightempinsulin": 0.8, 
        "bolussnooze": 0.241, 
        "iob": 0.997
      }, 
      {
        "netbasalinsulin": 0.6, 
        "activity": 0.0071, 
        "basaliob": 0.556, 
        "time": "2016-04-21T13:15:52.000Z", 
        "hightempinsulin": 0.85, 
        "bolussnooze": 0.171, 
        "iob": 1.011
      }, 
      {
        "netbasalinsulin": 0.65, 
        "activity": 0.0079, 
        "basaliob": 0.531, 
        "time": "2016-04-21T13:20:52.000Z", 
        "hightempinsulin": 0.85, 
        "bolussnooze": 0.113, 
        "iob": 0.972
      }, 
      {
        "netbasalinsulin": 0.7, 
        "activity": 0.0086, 
        "basaliob": 0.504, 
        "time": "2016-04-21T13:25:52.000Z", 
        "hightempinsulin": 0.85, 
        "bolussnooze": 0.067, 
        "iob": 0.929
      }, 
      {
        "netbasalinsulin": 0.7, 
        "activity": 0.0093, 
        "basaliob": 0.475, 
        "time": "2016-04-21T13:30:52.000Z", 
        "hightempinsulin": 0.85, 
        "bolussnooze": 0.033, 
        "iob": 0.883
      }, 
      {
        "netbasalinsulin": 0.75, 
        "activity": 0.0098, 
        "basaliob": 0.445, 
        "time": "2016-04-21T13:35:52.000Z", 
        "hightempinsulin": 0.85, 
        "bolussnooze": 0.011, 
        "iob": 0.834
      }, 
      {
        "netbasalinsulin": 0.75, 
        "activity": 0.0103, 
        "basaliob": 0.414, 
        "time": "2016-04-21T13:40:52.000Z", 
        "hightempinsulin": 0.85, 
        "bolussnooze": 0.001, 
        "iob": 0.782
      }, 
      {
        "netbasalinsulin": 0.8, 
        "activity": 0.0108, 
        "basaliob": 0.384, 
        "time": "2016-04-21T13:45:52.000Z", 
        "hightempinsulin": 0.85, 
        "bolussnooze": 0, 
        "iob": 0.728
      }, 
      {
        "netbasalinsulin": 0.8, 
        "activity": 0.0111, 
        "basaliob": 0.353, 
        "time": "2016-04-21T13:50:52.000Z", 
        "hightempinsulin": 0.85, 
        "bolussnooze": 0, 
        "iob": 0.672
      }, 
      {
        "netbasalinsulin": 0.85, 
        "activity": 0.0114, 
        "basaliob": 0.323, 
        "time": "2016-04-21T13:55:52.000Z", 
        "hightempinsulin": 0.85, 
        "bolussnooze": 0, 
        "iob": 0.615
      }, 
      {
        "netbasalinsulin": 0.85, 
        "activity": 0.0113, 
        "basaliob": 0.293, 
        "time": "2016-04-21T14:00:52.000Z", 
        "hightempinsulin": 0.85, 
        "bolussnooze": 0, 
        "iob": 0.558
      }, 
      {
        "netbasalinsulin": 0.8, 
        "activity": 0.0108, 
        "basaliob": 0.265, 
        "time": "2016-04-21T14:05:52.000Z", 
        "hightempinsulin": 0.8, 
        "bolussnooze": 0, 
        "iob": 0.504
      }, 
      {
        "netbasalinsulin": 0.75, 
        "activity": 0.0103, 
        "basaliob": 0.238, 
        "time": "2016-04-21T14:10:52.000Z", 
        "hightempinsulin": 0.75, 
        "bolussnooze": 0, 
        "iob": 0.453
      }, 
      {
        "netbasalinsulin": 0.7, 
        "activity": 0.0098, 
        "basaliob": 0.212, 
        "time": "2016-04-21T14:15:52.000Z", 
        "hightempinsulin": 0.7, 
        "bolussnooze": 0, 
        "iob": 0.403
      }, 
      {
        "netbasalinsulin": 0.65, 
        "activity": 0.0093, 
        "basaliob": 0.187, 
        "time": "2016-04-21T14:20:52.000Z", 
        "hightempinsulin": 0.65, 
        "bolussnooze": 0, 
        "iob": 0.357
      }, 
      {
        "netbasalinsulin": 0.65, 
        "activity": 0.0088, 
        "basaliob": 0.164, 
        "time": "2016-04-21T14:25:52.000Z", 
        "hightempinsulin": 0.65, 
        "bolussnooze": 0, 
        "iob": 0.313
      }, 
      {
        "netbasalinsulin": 0.65, 
        "activity": 0.0082, 
        "basaliob": 0.142, 
        "time": "2016-04-21T14:30:52.000Z", 
        "hightempinsulin": 0.65, 
        "bolussnooze": 0, 
        "iob": 0.272
      }, 
      {
        "netbasalinsulin": 0.65, 
        "activity": 0.0076, 
        "basaliob": 0.122, 
        "time": "2016-04-21T14:35:52.000Z", 
        "hightempinsulin": 0.65, 
        "bolussnooze": 0, 
        "iob": 0.234
      }, 
      {
        "netbasalinsulin": 0.65, 
        "activity": 0.007, 
        "basaliob": 0.104, 
        "time": "2016-04-21T14:40:52.000Z", 
        "hightempinsulin": 0.65, 
        "bolussnooze": 0, 
        "iob": 0.2
      }, 
      {
        "netbasalinsulin": 0.65, 
        "activity": 0.0063, 
        "basaliob": 0.088, 
        "time": "2016-04-21T14:45:52.000Z", 
        "hightempinsulin": 0.65, 
        "bolussnooze": 0, 
        "iob": 0.168
      }, 
      {
        "netbasalinsulin": 0.65, 
        "activity": 0.0057, 
        "basaliob": 0.073, 
        "time": "2016-04-21T14:50:52.000Z", 
        "hightempinsulin": 0.65, 
        "bolussnooze": 0, 
        "iob": 0.139
      }, 
      {
        "netbasalinsulin": 0.6, 
        "activity": 0.0051, 
        "basaliob": 0.06, 
        "time": "2016-04-21T14:55:52.000Z", 
        "hightempinsulin": 0.6, 
        "bolussnooze": 0, 
        "iob": 0.113
      }, 
      {
        "netbasalinsulin": 0.6, 
        "activity": 0.0046, 
        "basaliob": 0.048, 
        "time": "2016-04-21T15:00:52.000Z", 
        "hightempinsulin": 0.6, 
        "bolussnooze": 0, 
        "iob": 0.091
      }, 
      {
        "netbasalinsulin": 0.6, 
        "activity": 0.004, 
        "basaliob": 0.038, 
        "time": "2016-04-21T15:05:52.000Z", 
        "hightempinsulin": 0.6, 
        "bolussnooze": 0, 
        "iob": 0.071
      }, 
      {
        "netbasalinsulin": 0.55, 
        "activity": 0.0034, 
        "basaliob": 0.03, 
        "time": "2016-04-21T15:10:52.000Z", 
        "hightempinsulin": 0.55, 
        "bolussnooze": 0, 
        "iob": 0.054
      }, 
      {
        "netbasalinsulin": 0.5, 
        "activity": 0.0029, 
        "basaliob": 0.023, 
        "time": "2016-04-21T15:15:52.000Z", 
        "hightempinsulin": 0.5, 
        "bolussnooze": 0, 
        "iob": 0.039
      }, 
      {
        "netbasalinsulin": 0.45, 
        "activity": 0.0023, 
        "basaliob": 0.017, 
        "time": "2016-04-21T15:20:52.000Z", 
        "hightempinsulin": 0.45, 
        "bolussnooze": 0, 
        "iob": 0.028
      }, 
      {
        "netbasalinsulin": 0.4, 
        "activity": 0.0019, 
        "basaliob": 0.013, 
        "time": "2016-04-21T15:25:52.000Z", 
        "hightempinsulin": 0.4, 
        "bolussnooze": 0, 
        "iob": 0.018
      }, 
      {
        "netbasalinsulin": 0.35, 
        "activity": 0.0014, 
        "basaliob": 0.009, 
        "time": "2016-04-21T15:30:52.000Z", 
        "hightempinsulin": 0.35, 
        "bolussnooze": 0, 
        "iob": 0.011
      }, 
      {
        "netbasalinsulin": 0.3, 
        "activity": 0.001, 
        "basaliob": 0.006, 
        "time": "2016-04-21T15:35:52.000Z", 
        "hightempinsulin": 0.3, 
        "bolussnooze": 0, 
        "iob": 0.007
      }, 
      {
        "netbasalinsulin": 0.25, 
        "activity": 0.0006, 
        "basaliob": 0.004, 
        "time": "2016-04-21T15:40:52.000Z", 
        "hightempinsulin": 0.25, 
        "bolussnooze": 0, 
        "iob": 0.004
      }, 
      {
        "netbasalinsulin": 0.2, 
        "activity": 0.0003, 
        "basaliob": 0.002, 
        "time": "2016-04-21T15:45:52.000Z", 
        "hightempinsulin": 0.2, 
        "bolussnooze": 0, 
        "iob": 0.002
      }
    ], 
    "enacted": {
      "bg": 171, 
      "temp": "absolute", 
      "snoozeBG": 174, 
      "recieved": true, 
      "predBGs": {
        "IOB": [
          171, 
          168, 
          164, 
          161, 
          157, 
          153, 
          149, 
          145, 
          140, 
          136, 
          131, 
          126, 
          121, 
          116, 
          111, 
          106, 
          102, 
          97, 
          93, 
          89, 
          85, 
          81, 
          78, 
          74, 
          72, 
          69, 
          67, 
          65, 
          63, 
          62, 
          60, 
          59, 
          58, 
          58, 
          57
        ]
      }, 
      "reason": "COB: 0, Dev: 28, BGI: -1.33, Target: 115; Eventual BG 110>110 but Avg. Delta -3.00 < Exp. Delta -1.1; setting current basal of 0.36 as temp", 
      "rate": 0.325, 
      "eventualBG": 110, 
      "timestamp": "2016-04-21T12:54:46.000Z", 
      "duration": 30, 
      "tick": -3
    }
  }, 
  "mmtune": {
    "scanDetails": [
      [
        "916.540", 
        5, 
        -67
      ], 
      [
        "916.560", 
        5, 
        -59
      ], 
      [
        "916.580", 
        4, 
        -66
      ], 
      [
        "916.600", 
        5, 
        -57
      ], 
      [
        "916.620", 
        5, 
        -57
      ], 
      [
        "916.640", 
        5, 
        -57
      ], 
      [
        "916.660", 
        5, 
        -58
      ], 
      [
        "916.680", 
        5, 
        -60
      ], 
      [
        "916.700", 
        5, 
        -70
      ]
    ], 
    "setFreq": 916.64, 
    "timestamp": "2016-04-21T12:51:20.000Z", 
    "usedDefault": false
  }
}